{
  "neoforge:conditions": [
    {
      "type": "neoforge:mod_loaded",
      "modid": "kobolds"
    }
  ],
  "type": "neoforge:add_spawns",
  "biomes": "#adastramekanized:glacio_biomes",
  "spawners": [
    {
      "type": "kobolds:kobold",
      "weight": 20,
      "minCount": 2,
      "maxCount": 4
    },
    {
      "type": "kobolds:kobold_warrior",
      "weight": 10,
      "minCount": 1,
      "maxCount": 2
    },
    {
      "type": "kobolds:kobold_enchanter",
      "weight": 5,
      "minCount": 1,
      "maxCount": 1
    },
    {
      "type": "kobolds:kobold_engineer",
      "weight": 10,
      "minCount": 1,
      "maxCount": 2
    },
    {
      "type": "minecraft:polar_bear",
      "weight": 20,
      "minCount": 1,
      "maxCount": 2
    }
  ]
}